mcpcat/__init__.py
mcpcat/types.py
mcpcat/utils.py
mcpcat/modules/__init__.py
mcpcat/modules/compatibility.py
mcpcat/modules/constants.py
mcpcat/modules/context_parameters.py
mcpcat/modules/event_queue.py
mcpcat/modules/identify.py
mcpcat/modules/internal.py
mcpcat/modules/logging.py
mcpcat/modules/redaction.py
mcpcat/modules/session.py
mcpcat/modules/telemetry.py
mcpcat/modules/tools.py
mcpcat/modules/version_detection.py
mcpcat/modules/exporters/__init__.py
mcpcat/modules/exporters/datadog.py
mcpcat/modules/exporters/otlp.py
mcpcat/modules/exporters/sentry.py
mcpcat/modules/exporters/trace_context.py
mcpcat/modules/overrides/mcp_server.py
mcpcat/modules/overrides/community/monkey_patch.py
mcpcat/modules/overrides/community/tool_manager.py
mcpcat/modules/overrides/official/monkey_patch.py
mcpcat/thirdparty/__init__.py
mcpcat/thirdparty/ksuid/__init__.py
mcpcat/thirdparty/ksuid/baseconv.py
mcpcat/thirdparty/ksuid/ksuid.py
mcpcat-0.1.11.dist-info/METADATA
mcpcat-0.1.11.dist-info/WHEEL
mcpcat-0.1.11.dist-info/licenses/LICENSE
mcpcat-0.1.11.dist-info/RECORD
