Metadata-Version: 2.4
Name: mcpcat
Version: 0.1.11
Summary: Analytics Tool for MCP Servers - provides insights into MCP tool usage patterns
Project-URL: Homepage, https://github.com/MCPCat/mcpcat-python-sdk
Project-URL: Bug Tracker, https://github.com/MCPCat/mcpcat-python-sdk/issues
Project-URL: Repository, https://github.com/MCPCat/mcpcat-python-sdk
Author-email: MCPCat <support@mcpcat.io>
License: MIT
License-File: LICENSE
Classifier: Development Status :: 2 - Pre-Alpha
Classifier: Intended Audience :: Developers
Classifier: License :: OSI Approved :: MIT License
Classifier: Programming Language :: Python :: 3
Classifier: Programming Language :: Python :: 3.10
Classifier: Programming Language :: Python :: 3.11
Classifier: Programming Language :: Python :: 3.12
Requires-Python: >=3.10
Requires-Dist: mcp>=1.2.0
Requires-Dist: mcpcat-api==0.1.4
Requires-Dist: pydantic<2.12,>=2.0.0
Requires-Dist: requests>=2.31.0
Provides-Extra: community
Requires-Dist: fastmcp!=2.9.*,>=2.7.0; extra == 'community'
Provides-Extra: dev
Requires-Dist: freezegun>=1.2.0; extra == 'dev'
Requires-Dist: mypy>=1.0.0; extra == 'dev'
Requires-Dist: pytest-asyncio>=0.21.0; extra == 'dev'
Requires-Dist: pytest>=7.0.0; extra == 'dev'
Requires-Dist: ruff>=0.1.0; extra == 'dev'
